Metadata-Version: 1.1
Name: uproxy
Version: 0.3.99.13
Summary: An ipv4/ipv6 suppported http proxy server
Home-page: https://github.com/medlab/uproxy
Author: Cong Zhang
Author-email: congzhangzh@gmail.com
License: UNKNOWN
Keywords: http,https,ipv4/ipv6,proxy
Platform: UNKNOWN
Classifier: License :: OSI Approved :: BSD License
Classifier: Development Status :: 6 - Mature
Classifier: Environment :: Console
Classifier: Topic :: Utilities
Classifier: Programming Language :: Python :: 2.7
Classifier: Programming Language :: Python :: 3.6
Classifier: Programming Language :: Python :: 3.7
